scm/__init__.py
scm/auth.py
scm/client.py
scm/config/__init__.py
scm/config/deployment/__init__.py
scm/config/deployment/bandwidth_allocations.py
scm/config/deployment/bgp_routing.py
scm/config/deployment/internal_dns_servers.py
scm/config/deployment/network_locations.py
scm/config/deployment/remote_networks.py
scm/config/deployment/service_connections.py
scm/config/mobile_agent/__init__.py
scm/config/mobile_agent/agent_versions.py
scm/config/mobile_agent/auth_settings.py
scm/config/network/__init__.py
scm/config/network/ike_crypto_profile.py
scm/config/network/ike_gateway.py
scm/config/network/ipsec_crypto_profile.py
scm/config/network/nat_rules.py
scm/config/network/security_zone.py
scm/config/objects/__init__.py
scm/config/objects/address.py
scm/config/objects/address_group.py
scm/config/objects/application.py
scm/config/objects/application_filters.py
scm/config/objects/application_group.py
scm/config/objects/auto_tag_actions.py
scm/config/objects/dynamic_user_group.py
scm/config/objects/external_dynamic_lists.py
scm/config/objects/hip_object.py
scm/config/objects/hip_profile.py
scm/config/objects/http_server_profiles.py
scm/config/objects/log_forwarding_profile.py
scm/config/objects/quarantined_devices.py
scm/config/objects/region.py
scm/config/objects/schedules.py
scm/config/objects/service.py
scm/config/objects/service_group.py
scm/config/objects/syslog_server_profiles.py
scm/config/objects/tag.py
scm/config/security/__init__.py
scm/config/security/anti_spyware_profile.py
scm/config/security/decryption_profile.py
scm/config/security/dns_security_profile.py
scm/config/security/security_rule.py
scm/config/security/url_categories.py
scm/config/security/vulnerability_protection_profile.py
scm/config/security/wildfire_antivirus_profile.py
scm/config/setup/__init__.py
scm/config/setup/device.py
scm/config/setup/folder.py
scm/config/setup/label.py
scm/config/setup/snippet.py
scm/config/setup/variable.py
scm/exceptions/__init__.py
scm/insights/__init__.py
pan_scm_sdk-0.4.1.dist-info/LICENSE
pan_scm_sdk-0.4.1.dist-info/METADATA
pan_scm_sdk-0.4.1.dist-info/WHEEL
pan_scm_sdk-0.4.1.dist-info/RECORD
