Metadata-Version: 2.3
Name: pan-scm-sdk
Version: 0.4.1
Summary: Python SDK for Palo Alto Networks Strata Cloud Manager.
License: Apache 2.0
Keywords: paloaltonetworks,stratacloudmanager,scm
Author: Calvin Remsburg
Author-email: calvin@cdot.io
Requires-Python: >=3.10,<4.0
Classifier: License :: Other/Proprietary License
Classifier: Programming Language :: Python :: 3
Classifier: Programming Language :: Python :: 3.10
Classifier: Programming Language :: Python :: 3.11
Classifier: Programming Language :: Python :: 3.12
Classifier: Programming Language :: Python :: 3.13
Requires-Dist: cryptography (>=46.0.0,<47.0.0)
Requires-Dist: oauthlib (>=3.3.0,<4.0.0)
Requires-Dist: pydantic (>=2.12.0,<3.0.0)
Requires-Dist: pyjwt (>=2.9.0,<3.0.0)
Requires-Dist: requests-oauthlib (>=2.0.0,<3.0.0)
Requires-Dist: setuptools (>=78.1.1,<79.0.0)
Project-URL: Documentation, https://cdot65.github.io/pan-scm-sdk/
Project-URL: Homepage, https://github.com/cdot65/pan-scm-sdk
Project-URL: Repository, https://github.com/cdot65/pan-scm-sdk
